listconfig
