Metadata-Version: 2.1
Name: listconfig
Version: 0.0.4
Summary: Format .config → config list with description and metadata
Home-page: https://github.com/puhitaku/listconfig
Author: Takumi Sueda
Author-email: puhitaku@gmail.com
License: UNKNOWN
Platform: UNKNOWN
Classifier: License :: OSI Approved :: MIT License
Classifier: Programming Language :: Python :: 3
Classifier: Programming Language :: Python :: 3.7
Classifier: Programming Language :: Python :: 3.8
Classifier: Programming Language :: Python :: 3.9
Classifier: Topic :: Utilities
Requires-Python: >=3.7
